nonebot_plugin_xibao/SourceHanSansSC-Regular.otf
nonebot_plugin_xibao/__init__.py
nonebot_plugin_xibao/beibao_bg.png
nonebot_plugin_xibao/xibao_bg.png
nonebot_plugin_xibao-1.1.1.dist-info/METADATA
nonebot_plugin_xibao-1.1.1.dist-info/WHEEL
nonebot_plugin_xibao-1.1.1.dist-info/RECORD
