Metadata-Version: 2.4
Name: nonebot-plugin-xibao
Version: 1.1.1
Summary: 生成一张喜报（或者是悲报）！
Author: sp2dev
Author-email: theinsp2@outlook.com
Requires-Python: >=3.9, <4.0
Classifier: Programming Language :: Python :: 3
Classifier: Programming Language :: Python :: 3.9
Classifier: Programming Language :: Python :: 3.10
Classifier: Programming Language :: Python :: 3.11
Classifier: Programming Language :: Python :: 3.12
Classifier: Programming Language :: Python :: 3.13
Classifier: Programming Language :: Python :: 3.14
Requires-Dist: nonebot-plugin-send-anything-anywhere (>=0.7.0)
Requires-Dist: nonebot2 (>=2.4.2,<3.0.0)
Requires-Dist: opencv-python-headless (>=4.0)
Requires-Dist: skia-python (>=130.0)
